pypetl/__init__.py
pypetl/config.py
pypetl/engine.py
pypetl/extract.py
pypetl/core/__init__.py
pypetl/core/aws.py
pypetl/core/db.py
pypetl/core/file.py
pypetl/core/log.py
pypetl/core/tunnel.py
pypetl/io/__init__.py
pypetl/io/db.py
pypetl/transform/__init__.py
pypetl/transform/convert.py
pypetl_canary-0.0.0b6.dist-info/LICENSE
pypetl_canary-0.0.0b6.dist-info/METADATA
pypetl_canary-0.0.0b6.dist-info/WHEEL
pypetl_canary-0.0.0b6.dist-info/top_level.txt
pypetl_canary-0.0.0b6.dist-info/RECORD
